{"content": ["第194章 阎王爷似乎变了？", "眨眼之间，刚刚还满目疮痍的土地已然焕然一新，犹如未曾经历过任何破坏一般平整。", "事情完成之后，临澜面无表情地站在原地，嘴角缓缓泛起一丝不易察觉的冷笑，用充满挑衅的口吻问道：“现在这样，可以了吧？”", "闫闻璟扫了一眼后微微颔首，表示可以。", "临澜见状，眼底突然闪过一抹如野兽般嗜血的危险光芒，压低声音咬牙切齿地道：“闫闻璟，今日之事我记下了。你最好祈祷不要落入我的手中，否则……呵！”", "话音未落，一股浓烈的杀气瞬间在两人之间弥漫开来。", "秦羽涅皱眉，身体不由自主地向前微倾，宛如一只护雏的母鸡般，小心翼翼地将闫闻璟遮挡在了身后。", "尽管在知道临澜身份后，她心中有些恐惧，但仍然强忍着内心的惧意，挺直了脊梁，颤声说道：“你想做什么？我告诉你，你可别乱来。”", "一直以来对临澜的挑衅不以为意的闫闻璟，在发现身前多了一抹娇小而坚定的身影后愣了愣，竟然丝毫没有被临澜冒犯的不悦，反倒是在听到秦羽涅的话后，心底涌起一丝愉悦。", "崔判官见状，有些担心秦羽涅，问孟婆：“我们不去帮忙吗？”", "孟婆瞥了一眼后，欣赏着自己的指甲，慢悠悠的说：“急什么？你没发现阎王爷现在心情很好吗？有阎王爷在，还需要你出手保护小羽涅？而更何况以我对临澜的了解，他不会动手的，他这人有点孤傲清高，对秦羽涅这种没什么灵力，手无缚鸡之力的女子不屑出手，那样会有损他的威名。”", "听到这话，崔判官想了想似乎是这样，以往只听到临澜又挑战了谁谁谁，又攻打了哪，可从来没听说过他对没灵力的人类女子动手，想到这里，他也不着急了。", "两人的声音小，听到的人不多。", "而临澜刚刚所散发出的浓烈杀意如同凛冽寒风席卷全场，众人皆清晰地感受到了那股扑面而来的威压与寒意，狐九原本还有些犹豫要不要过去，白泊仿佛看穿了他的心思，动作优雅地伸出手，轻柔且缓慢地摩挲着狐九的脊背，语气从容不迫，仿若在耐心地向他解释道：“有闫闻璟在，用不着你操心。”", "闻言，狐九见其他人都没动作，连孟婆他们都不着急，这时才发现闫闻璟的位置似乎动了一下，弧度虽然很小，但其实是将秦羽涅整个纳入了包围圈。", "就算临澜想动手做什么，也不会牵连到她。", "烈焰虽然对比而言更不喜欢临澜，但能够看到他们俩任何一个吃瘪，他都会很高兴，自然不会管这些。", "其他人则基本都跟白泊他们想法差不多，有闫闻璟在，用不着他们出手，贸然出手反倒不好。", "毕竟显然闫闻璟被‘保护’还挺正乐得其中。", "然而，对于这一切暗潮涌动，秦羽涅却是浑然不觉。", "因为她发现自己的肩膀上多出来一双温热的大手，那掌心的温度透过单薄的衣物，源源不断地传递至她的全身，带来一阵酥麻与不适。", "这种陌生的触感令她浑身不自在起来，下意识地便想要扭动身体挣脱开来。", "可是，肩膀上传来的那股微微的力道，虽不至于沉重压抑，但却犹如铁钳一般紧紧锁住了她，使得她根本动弹不得分毫，整个人僵在原地。", "临澜将在场众人的神态尽收眼底，特别是当他注意到闫闻璟身上那明显变得愉悦轻松的气息时，心中不禁涌起更多的不满和恼怒，感情他搁这给闫闻璟充当陪衬的啊！"], "title": "194.第194章 阎王爷似乎变了？", "prev": "https://www.22biqu.com/biqu82443/40557767.html", "next": "https://www.22biqu.com/biqu82443/40557768_2.html", "toc_url": "https://www.22biqu.com/biqu82443/"}