{"content": ["第50章 有什么想要的？", "秦羽涅想起什么似的，又凑过去问了句，“你刚说可以给我打折，是所有人都可以打折吗？”", "闫闻璟懒洋洋的掀起眼皮看她一眼，“你想让谁死？”", "秦羽涅连忙摇头，“也没有，就是问一下，嗯问一下。”", "“哦，等你需要的时候再说。”闫闻璟慢悠悠的瞥她一眼，“这么慢，我什么时候才能吃上饭？”", "话音刚落，秦羽涅手上重量一轻，随后她整个人飞了起来。", "“啊——”", "秦羽涅就这么眼睁睁看着她的小拖车漂浮起来，她也跟着飞了起来。", "而闫闻璟早在之前就已经往他们两人周身施了法，其他人看不到也听不到他们说话，更别提看到他们了。", "因此，也没人知道有个小拖车诡异的飘在天上。", "秦羽涅有了第一次的经验，这次只是慌了一下，就淡定的左顾右看起来。", "她唯一的要求就是，下次能不能不要这么粗暴！", "对她稍微温柔点！", "她是女孩子啊！", "不过，这速度一下就提升了数十倍，以往她要走十几二十分钟的路程，她不过一眨眼间，就到了。", "落在她家院子里的瞬间，秦羽涅极其缓慢的眨了眨眼：嗯……真快啊……", "闫闻璟仿佛到自己家一般自如，率先朝里面走去，秦羽涅迟了一步，才拉着脚边的拖车往里走。", "期间他还嫌她动作太慢了，顺手将拖车送到了它该去的位置。", "秦羽涅眼看着东西自动归位，沉默了片刻，再一次感叹有法力真好，这些琐事不用亲自动手，只需要施个法就好了。", "这想法只是一闪而过，随后她就默默洗了手去厨房给阎王爷做饭。", "顺便多做了一点，把她的晚餐也做了，省得她一会儿还要再做一遍。", "因为阎王爷的缘故，秦羽涅难得拿出比较贵的盘子，特意做了摆盘。", "她虽然更擅长做家常菜，但是一些不那么复杂的菜她也都会，她学这些总是特别简单，只要看一眼基本就能复盘，但是要想做好，还是需要一点时间功夫。", "秦羽涅做好端出去，看到闫闻璟眼观鼻鼻观心坐在那，心里竟然有种阎王爷还挺‘乖’的既视感。", "她连忙摇摇头，这都是错觉。", "听到声音，闫闻璟转头看过去，就看见秦羽涅在那摇头，眼底闪过一丝不解。", "秦羽涅注意到他的视线，连忙将菜端到桌上放下，递上一双筷子，“阎王爷，请用。”", "这里虽然食材没有大城市多，但是胜在口感好，是大棚催熟的不能比的。", "“嗯。”闫闻璟应声，发现桌上只有他自己的份量，问：“你不吃？”", "秦羽涅解释说：“我的还在厨房，等您吃了我再吃。”", "闫闻璟微微蹙眉，“拿出来一起吃，我没这么讲究。”", "秦羽涅：“……”", "说没这么讲究的人，是不是忘了，他自己上一秒还说她把盒饭给他们拿弄脏了，为此她才专门做的这顿饭。", "秦羽涅见他不动筷，似乎是真打算等她一起吃，只好转身进厨房将她的那份端出来。", "看到她把饭菜放桌上坐下，闫闻璟这才吃了第一口。"], "title": "第50章 有什么想要的？", "prev": "https://www.22biqu.com/biqu82443/40491077.html", "next": "https://www.22biqu.com/biqu82443/40491078_2.html", "toc_url": "https://www.22biqu.com/biqu82443/"}